claude_saga/__init__.py
claude_saga/__version__.py
claude_saga-0.1.2.dist-info/METADATA
claude_saga-0.1.2.dist-info/WHEEL
claude_saga-0.1.2.dist-info/licenses/LICENSE
claude_saga-0.1.2.dist-info/RECORD
