Metadata-Version: 2.4
Name: claude-saga
Version: 0.1.2
Summary: A Redux Saga-like effect system for Python, designed for Claude Code hooks
Project-URL: Homepage, https://github.com/listfold/claude-saga
Project-URL: Repository, https://github.com/listfold/claude-saga
Project-URL: Issues, https://github.com/listfold/claude-saga/issues
Author: Iain
License: MIT
License-File: LICENSE
Keywords: claude,effects,functional,generator,hooks,saga,side-effects
Classifier: Development Status :: 3 - Alpha
Classifier: Intended Audience :: Developers
Classifier: License :: OSI Approved :: MIT License
Classifier: Programming Language :: Python :: 3
Classifier: Programming Language :: Python :: 3.12
Classifier: Programming Language :: Python :: 3.13
Classifier: Topic :: Software Development :: Libraries
Classifier: Topic :: Software Development :: Libraries :: Python Modules
Classifier: Typing :: Typed
Requires-Python: >=3.12
Provides-Extra: dev
Requires-Dist: pytest>=8.0.0; extra == 'dev'
Requires-Dist: ruff>=0.4.0; extra == 'dev'
